hmjr/Entries.py
hmjr/Query.py
hmjr/SortedBy.py
hmjr/__init__.py
hmjr/hmjr.py
hmjr/tests/__init__.py
hmjr/tests/queries.py
hmjr/tests/sort.py
hmjr/tests/subCollections.py
hmjr-0.1.3.dist-info/METADATA
hmjr-0.1.3.dist-info/WHEEL
hmjr-0.1.3.dist-info/top_level.txt
hmjr-0.1.3.dist-info/RECORD
